cayleypy/__init__.py
cayleypy/bfs_result.py
cayleypy/bfs_result_test.py
cayleypy/cayley_graph.py
cayleypy/cayley_graph_def.py
cayleypy/cayley_graph_def_test.py
cayleypy/cayley_graph_test.py
cayleypy/cayley_path.py
cayleypy/create_graph.py
cayleypy/create_graph_test.py
cayleypy/datasets.py
cayleypy/datasets_test.py
cayleypy/graphs_lib.py
cayleypy/graphs_lib_test.py
cayleypy/hasher.py
cayleypy/permutation_utils.py
cayleypy/permutation_utils_test.py
cayleypy/predictor.py
cayleypy/predictor_test.py
cayleypy/string_encoder.py
cayleypy/string_encoder_test.py
cayleypy/torch_utils.py
cayleypy/algo/__init__.py
cayleypy/algo/beam_search.py
cayleypy/algo/beam_search_result.py
cayleypy/algo/beam_search_test.py
cayleypy/algo/bfs_bitmask.py
cayleypy/algo/bfs_bitmask_test.py
cayleypy/algo/bfs_mitm.py
cayleypy/algo/bfs_mitm_test.py
cayleypy/algo/bfs_numpy.py
cayleypy/algo/bfs_numpy_test.py
cayleypy/algo/find_path.py
cayleypy/algo/find_path_test.py
cayleypy/algo/interactive_bfs.py
cayleypy/algo/interactive_bfs_test.py
cayleypy/algo/random_walks.py
cayleypy/data/all_cycles_cayley_growth.csv
cayleypy/data/all_transpositions_cayley_growth.csv
cayleypy/data/block_interchange_cayley_growth.csv
cayleypy/data/burnt_pancake_cayley_growth.csv
cayleypy/data/consecutive_k_cycles_cayley_growth.csv
cayleypy/data/coxeter_cayley_growth.csv
cayleypy/data/cyclic_coxeter_cayley_growth.csv
cayleypy/data/derangements_cayley_growth.csv
cayleypy/data/full_reversals_cayley_growth.csv
cayleypy/data/globes_growth.csv
cayleypy/data/heisenberg_growth.csv
cayleypy/data/hungarian_rings_growth.csv
cayleypy/data/increasing_k_cycles_cayley_growth.csv
cayleypy/data/involutive_derangements_cayley_growth.csv
cayleypy/data/larx_cayley_growth.csv
cayleypy/data/lrx_cayley_growth.csv
cayleypy/data/lrx_coset_growth.csv
cayleypy/data/lx_cayley_growth.csv
cayleypy/data/pancake_cayley_growth.csv
cayleypy/data/puzzles_growth.csv
cayleypy/data/rapaport_m1_cayley_growth.csv
cayleypy/data/rapaport_m2_cayley_growth.csv
cayleypy-0.1.0.dist-info/licenses/LICENSE
cayleypy-0.1.0.dist-info/METADATA
cayleypy-0.1.0.dist-info/WHEEL
cayleypy-0.1.0.dist-info/top_level.txt
cayleypy-0.1.0.dist-info/RECORD
