Metadata-Version: 2.4
Name: cayleypy
Version: 0.1.0
Summary: Library for studying Cayley graphs and Schreier coset graphs
Author: CayleyPy Foundation
License: MIT License
Project-URL: Homepage, https://github.com/cayleypy/cayleypy
Project-URL: Documentation, https://cayleypy.github.io/cayleypy-docs/api.html
Classifier: Development Status :: 3 - Alpha
Classifier: License :: OSI Approved :: MIT License
Classifier: Topic :: Scientific/Engineering :: Mathematics
Requires-Python: >=3.9
License-File: LICENSE
Requires-Dist: h5py
Requires-Dist: kagglehub
Requires-Dist: numba
Requires-Dist: numpy
Requires-Dist: scipy
Provides-Extra: torch
Requires-Dist: torch; extra == "torch"
Provides-Extra: lint
Requires-Dist: black; extra == "lint"
Requires-Dist: mypy==1.15.0; extra == "lint"
Requires-Dist: pylint; extra == "lint"
Provides-Extra: test
Requires-Dist: pytest; extra == "test"
Requires-Dist: pytest-benchmark; extra == "test"
Provides-Extra: dev
Requires-Dist: coverage; extra == "dev"
Requires-Dist: networkx; extra == "dev"
Requires-Dist: setuptools; extra == "dev"
Provides-Extra: docs
Requires-Dist: sphinx; extra == "docs"
Requires-Dist: sphinx_rtd_theme; extra == "docs"
Requires-Dist: sphinx_markdown_parser; extra == "docs"
Dynamic: license-file
